[
    {
        "round_id": "22199",
        "heat_id": "94250",
        "athlete_id": "4133",
        "athlete_name": "E. Ewing",
        "total_score": 14.5
    },
    {
        "round_id": "22199",
        "heat_id": "94250",
        "athlete_id": "139",
        "athlete_name": "N. Young",
        "total_score": 11.43
    },
    {
        "round_id": "22199",
        "heat_id": "94250",
        "athlete_id": "1717",
        "athlete_name": "C. Munoz",
        "total_score": 8.54
    },
    {
        "round_id": "22199",
        "heat_id": "94251",
        "athlete_id": "3165",
        "athlete_name": "G. Colapinto",
        "total_score": 15.66
    },
    {
        "round_id": "22199",
        "heat_id": "94251",
        "athlete_id": "3955",
        "athlete_name": "S. Moniz",
        "total_score": 11.03
    },
    {
        "round_id": "22199",
        "heat_id": "94251",
        "athlete_id": "616",
        "athlete_name": "M. Huscenot",
        "total_score": 10.37
    },
    {
        "round_id": "22199",
        "heat_id": "94252",
        "athlete_id": "1291",
        "athlete_name": "C. Ibelli",
        "total_score": 10.94
    },
    {
        "round_id": "22199",
        "heat_id": "94252",
        "athlete_id": "1760",
        "athlete_name": "R. Callinan",
        "total_score": 13.27
    },
    {
        "round_id": "22199",
        "heat_id": "94252",
        "athlete_id": "1957",
        "athlete_name": "E. Lau",
        "total_score": 10.34
    },
    {
        "round_id": "22199",
        "heat_id": "94253",
        "athlete_id": "9167",
        "athlete_name": "J. Chianca",
        "total_score": 11.67
    },
    {
        "round_id": "22199",
        "heat_id": "94253",
        "athlete_id": "3737",
        "athlete_name": "M. McGillivray",
        "total_score": 10.84
    },
    {
        "round_id": "22199",
        "heat_id": "94253",
        "athlete_id": "9079",
        "athlete_name": "D. Moffat",
        "total_score": 12.33
    },
    {
        "round_id": "22199",
        "heat_id": "94254",
        "athlete_id": "1456",
        "athlete_name": "F. Toledo",
        "total_score": 11.24
    },
    {
        "round_id": "22199",
        "heat_id": "94254",
        "athlete_id": "2618",
        "athlete_name": "I. Gentil",
        "total_score": 10.36
    },
    {
        "round_id": "22199",
        "heat_id": "94254",
        "athlete_id": "297",
        "athlete_name": "O. Wright",
        "total_score": 12.84
    },
    {
        "round_id": "22199",
        "heat_id": "94255",
        "athlete_id": "3442",
        "athlete_name": "J. Robinson",
        "total_score": 12.56
    },
    {
        "round_id": "22199",
        "heat_id": "94255",
        "athlete_id": "553",
        "athlete_name": "K. Slater",
        "total_score": 9.6
    },
    {
        "round_id": "22199",
        "heat_id": "94255",
        "athlete_id": "1078",
        "athlete_name": "X. Huxtable",
        "total_score": 11.5
    },
    {
        "round_id": "22199",
        "heat_id": "94256",
        "athlete_id": "1737",
        "athlete_name": "I. Ferreira",
        "total_score": 10.8
    },
    {
        "round_id": "22199",
        "heat_id": "94256",
        "athlete_id": "2838",
        "athlete_name": "C. O'Leary",
        "total_score": 10.0
    },
    {
        "round_id": "22199",
        "heat_id": "94256",
        "athlete_id": "1164",
        "athlete_name": "K. Andino",
        "total_score": 11.64
    },
    {
        "round_id": "22199",
        "heat_id": "94257",
        "athlete_id": "9654",
        "athlete_name": "C. Robson",
        "total_score": 11.93
    },
    {
        "round_id": "22199",
        "heat_id": "94257",
        "athlete_id": "564",
        "athlete_name": "J. Smith",
        "total_score": 12.47
    },
    {
        "round_id": "22199",
        "heat_id": "94257",
        "athlete_id": "2251",
        "athlete_name": "M. Rodrigues",
        "total_score": 14.47
    },
    {
        "round_id": "22199",
        "heat_id": "94258",
        "athlete_id": "2656",
        "athlete_name": "L. Fioravanti",
        "total_score": 11.37
    },
    {
        "round_id": "22199",
        "heat_id": "94258",
        "athlete_id": "9112",
        "athlete_name": "R. Waida",
        "total_score": 10.6
    },
    {
        "round_id": "22199",
        "heat_id": "94258",
        "athlete_id": "3812",
        "athlete_name": "J. Baker",
        "total_score": 13.0
    },
    {
        "round_id": "22199",
        "heat_id": "94259",
        "athlete_id": "3994",
        "athlete_name": "Y. Dora",
        "total_score": 13.83
    },
    {
        "round_id": "22199",
        "heat_id": "94259",
        "athlete_id": "8784",
        "athlete_name": "S. Pupo",
        "total_score": 13.67
    },
    {
        "round_id": "22199",
        "heat_id": "94259",
        "athlete_id": "3122",
        "athlete_name": "J. Marshall",
        "total_score": 10.0
    },
    {
        "round_id": "22199",
        "heat_id": "94260",
        "athlete_id": "1085",
        "athlete_name": "G. Medina",
        "total_score": 13.0
    },
    {
        "round_id": "22199",
        "heat_id": "94260",
        "athlete_id": "3896",
        "athlete_name": "K. Igarashi",
        "total_score": 16.4
    },
    {
        "round_id": "22199",
        "heat_id": "94260",
        "athlete_id": "6963",
        "athlete_name": "L. O'Brien",
        "total_score": 12.43
    },
    {
        "round_id": "22199",
        "heat_id": "94261",
        "athlete_id": "199",
        "athlete_name": "J. Florence",
        "total_score": 16.26
    },
    {
        "round_id": "22199",
        "heat_id": "94261",
        "athlete_id": "8801",
        "athlete_name": "M. Cibilic",
        "total_score": 12.17
    },
    {
        "round_id": "22199",
        "heat_id": "94261",
        "athlete_id": "3962",
        "athlete_name": "B. Mamiya",
        "total_score": 12.1
    }
]